agb/__init__.py
agb/agb.py
agb/config.py
agb/exceptions.py
agb/session.py
agb/session_params.py
agb/api/__init__.py
agb/api/base_service.py
agb/api/client.py
agb/api/http_client.py
agb/api/models/__init__.py
agb/api/models/call_mcp_tool_request.py
agb/api/models/call_mcp_tool_response.py
agb/api/models/create_session_request.py
agb/api/models/create_session_response.py
agb/api/models/get_mcp_resource_request.py
agb/api/models/get_mcp_resource_response.py
agb/api/models/list_mcp_tools_request.py
agb/api/models/list_mcp_tools_response.py
agb/api/models/release_session_request.py
agb/api/models/release_session_response.py
agb/model/__init__.py
agb/model/response.py
agb/modules/__init__.py
agb/modules/code.py
agb/modules/command.py
agb/modules/file_system.py
agb/modules/oss.py
agb_sdk-0.1.0.dist-info/licenses/LICENSE
agb_sdk-0.1.0.dist-info/METADATA
agb_sdk-0.1.0.dist-info/WHEEL
agb_sdk-0.1.0.dist-info/top_level.txt
agb_sdk-0.1.0.dist-info/RECORD
